echo_artistry/__init__.py
echo_artistry/exceptions/__init__.py
echo_artistry/exceptions/openai_exceptions.py
echo_artistry/generators/__init__.py
echo_artistry/generators/comic_image_generator.py
echo_artistry/generators/comic_story_generator.py
echo_artistry/generators/file_name_generator.py
echo_artistry/main.py
echo_artistry/services/__init__.py
echo_artistry/services/cost_management.py
echo_artistry/services/token_counter.py
echo_artistry/services/transcriber.py
echo_artistry/utils/__init__.py
echo_artistry/utils/helper.py
echo_artistry/utils/openai_client.py
echo_artistry-0.0.1.dist-info/LICENSE
echo_artistry-0.0.1.dist-info/METADATA
echo_artistry-0.0.1.dist-info/WHEEL
echo_artistry-0.0.1.dist-info/entry_points.txt
echo_artistry-0.0.1.dist-info/RECORD
