Metadata-Version: 2.1
Name: echo-artistry
Version: 0.0.1
Summary: EchoArtistry is an innovative tool that transforms spoken words into captivating visual stories.
Author: Jurik-001
Requires-Python: >=3.10,<4.0
Classifier: Programming Language :: Python :: 3
Classifier: Programming Language :: Python :: 3.10
Classifier: Programming Language :: Python :: 3.11
Classifier: Programming Language :: Python :: 3.12
Requires-Dist: openai (>=1.6.1,<2.0.0)
Requires-Dist: openai-whisper (==20231117)
Requires-Dist: pillow (>=10.1.0,<11.0.0)
